setup.py
hsrogl/__init__.py
hsrogl/bool.py
hsrogl/math.py
hsrogl/ui.py
hsrogl/unicode.py
hsrogl.egg-info/PKG-INFO
hsrogl.egg-info/SOURCES.txt
hsrogl.egg-info/dependency_links.txt
hsrogl.egg-info/top_level.txt