Metadata-Version: 2.1
Name: hsrogl
Version: 1.0.1
Summary: an full package with tools and functions
Author: Hansha
Author-email: 3582930858@qq.com
Keywords: python,math,ui,bool,unicode,windows,mac,linux,unix
Classifier: Development Status :: 1 - Planning
Classifier: Intended Audience :: Developers
Classifier: Programming Language :: Python :: 3
Classifier: Operating System :: Unix
Classifier: Operating System :: MacOS :: MacOS X
Classifier: Operating System :: Microsoft :: Windows
